arachne_runtime/__init__.py
arachne_runtime/module/__init__.py
arachne_runtime/module/factory.py
arachne_runtime/module/onnx.py
arachne_runtime/module/tflite.py
arachne_runtime/module/tvm.py
arachne_runtime/rpc/__init__.py
arachne_runtime/rpc/client/__init__.py
arachne_runtime/rpc/client/client.py
arachne_runtime/rpc/client/stubmgr/__init__.py
arachne_runtime/rpc/client/stubmgr/file.py
arachne_runtime/rpc/client/stubmgr/serverstatus.py
arachne_runtime/rpc/logger.py
arachne_runtime/rpc/protobuf/__init__.py
arachne_runtime/rpc/protobuf/definition/codegen.sh
arachne_runtime/rpc/protobuf/definition/fileserver.proto
arachne_runtime/rpc/protobuf/definition/msg_response.proto
arachne_runtime/rpc/protobuf/definition/runtime.proto
arachne_runtime/rpc/protobuf/definition/runtime_message.proto
arachne_runtime/rpc/protobuf/definition/server_status.proto
arachne_runtime/rpc/protobuf/definition/stream_data.proto
arachne_runtime/rpc/protobuf/fileserver_pb2.py
arachne_runtime/rpc/protobuf/fileserver_pb2_grpc.py
arachne_runtime/rpc/protobuf/msg_response_pb2.py
arachne_runtime/rpc/protobuf/msg_response_pb2_grpc.py
arachne_runtime/rpc/protobuf/runtime_message_pb2.py
arachne_runtime/rpc/protobuf/runtime_message_pb2_grpc.py
arachne_runtime/rpc/protobuf/runtime_pb2.py
arachne_runtime/rpc/protobuf/runtime_pb2_grpc.py
arachne_runtime/rpc/protobuf/server_status_pb2.py
arachne_runtime/rpc/protobuf/server_status_pb2_grpc.py
arachne_runtime/rpc/protobuf/stream_data_pb2.py
arachne_runtime/rpc/protobuf/stream_data_pb2_grpc.py
arachne_runtime/rpc/server.py
arachne_runtime/rpc/servicer/__init__.py
arachne_runtime/rpc/servicer/file.py
arachne_runtime/rpc/servicer/serverstatus.py
arachne_runtime/rpc/servicer/servicer.py
arachne_runtime/rpc/utils/nparray.py
arachne_runtime/utils/__init__.py
arachne_runtime/utils/version_utils.py
arachne_runtime-0.1.1.dist-info/LICENSE
arachne_runtime-0.1.1.dist-info/WHEEL
arachne_runtime-0.1.1.dist-info/METADATA
arachne_runtime-0.1.1.dist-info/RECORD
