Metadata-Version: 2.1
Name: arachne-runtime
Version: 0.1.1
Summary: A thin library for executing different types of DNN models from a common API
Home-page: https://github.com/fixstars/arachne-runtime
License: MIT
Author: Takafumi Kubota
Author-email: takafumi.kubota@fixstars.com
Requires-Python: >=3.6.3,<3.10
Classifier: License :: OSI Approved :: MIT License
Classifier: Programming Language :: Python :: 3
Classifier: Programming Language :: Python :: 3.7
Classifier: Programming Language :: Python :: 3.8
Classifier: Programming Language :: Python :: 3.9
Requires-Dist: PyYAML (>=6.0,<7.0)
Requires-Dist: grpcio (<1.45.0)
Requires-Dist: grpcio-tools (<1.45.0)
Requires-Dist: numpy (<1.22.3)
Requires-Dist: packaging (>=21.3,<22.0)
Project-URL: Repository, https://github.com/fixstars/arachne-runtime
